clumper/__init__.py
clumper/clump.py
clumper/decorators.py
clumper/error.py
clumper/sequence.py
clumper/this.py
clumper-0.2.15.dist-info/LICENSE
clumper-0.2.15.dist-info/METADATA
clumper-0.2.15.dist-info/WHEEL
clumper-0.2.15.dist-info/top_level.txt
clumper-0.2.15.dist-info/RECORD
