Metadata-Version: 2.1
Name: clumper
Version: 0.2.15
Summary: UNKNOWN
Home-page: UNKNOWN
License: UNKNOWN
Platform: UNKNOWN
License-File: LICENSE
Provides-Extra: all
Requires-Dist: PyYAML (>=5.3.1) ; extra == 'all'
Provides-Extra: dev
Requires-Dist: pytest (>=5.4.3) ; extra == 'dev'
Requires-Dist: black (>=19.10b0) ; extra == 'dev'
Requires-Dist: flake8 (>=3.8.3) ; extra == 'dev'
Requires-Dist: mktestdocs (>=0.1.0) ; extra == 'dev'
Requires-Dist: interrogate (>=1.2.0) ; extra == 'dev'
Requires-Dist: jupyterlab (>=2.2.0) ; extra == 'dev'
Requires-Dist: pre-commit (>=2.6.0) ; extra == 'dev'
Requires-Dist: mkdocs (>=1.1) ; extra == 'dev'
Requires-Dist: mkdocs-material (>=4.6.3) ; extra == 'dev'
Requires-Dist: mkdocstrings (>=0.8.0) ; extra == 'dev'
Requires-Dist: PyYAML (>=5.3.1) ; extra == 'dev'
Provides-Extra: test
Requires-Dist: pytest (>=5.4.3) ; extra == 'test'
Requires-Dist: black (>=19.10b0) ; extra == 'test'
Requires-Dist: flake8 (>=3.8.3) ; extra == 'test'
Requires-Dist: mktestdocs (>=0.1.0) ; extra == 'test'
Requires-Dist: interrogate (>=1.2.0) ; extra == 'test'
Provides-Extra: yaml
Requires-Dist: PyYAML (>=5.3.1) ; extra == 'yaml'
